{
  "videoId": "06VnkTfzweI",
  "title": "Flight Simulator 2020 - How to - Cirrus SR22 - Set flight plan",
  "description": "In this how to we are going to look how we can configure our flight plan manually in our navigation system from our  Cirrus SR22.\n\nRoute being configure will be from Courchevel (LFLJ) to Grenoble Le Versoud Airport (LFLG).\n\n🔔 If you like this video please consider to subscribe to my channel: https://bit.ly/34eNWDP 🔔 \n\nTutorials playlist: https://bit.ly/32nmUHH\nWebsite: https://highintheflightsimsky.nl\n\n#FlightSimulator2020 #FlightSim #FS2020",
  "thumbnail": "https://i.ytimg.com/vi/06VnkTfzweI/sddefault.jpg",
  "thumbnailMedium": "https://i.ytimg.com/vi/06VnkTfzweI/mqdefault.jpg",
  "publishedAt": "2020-09-11T20:08:05.000Z",
  "duration": 584,
  "tags": [
    "Flight Simulator 2020",
    "flight plan",
    "microsoft flight simulator",
    "flight simulator",
    "microsoft flight simulator 2020",
    "tutorials",
    "flight training",
    "flight sim 2020",
    "how to set flight plan in flight sim 2020",
    "how to set a flight plan in microsoft flight simulator",
    "courchevel airport",
    "Grenoble Le Versoud Airport",
    "how to set flight plan in Cirrus SR22",
    "Garmin G1000",
    "Garmin",
    "How to set a flight plan in Garmin G1000",
    "flight planning"
  ],
  "featured": false
}