{
  "videoId": "14KSXN6C9b4",
  "title": "Flight Simulator 2020 - How to - A32NX - Continue your flight plan after loading your flight from a",
  "description": "In this video we will have a look how you can continue your flight plan if you loaded a saved flight within MSFS. Besides switching on the autopilot which is probably the easiest piece you will likely face issues that the autopilot doesn't follow the flight plan anymore. In this video I will show you how to resolve that issue.\n\nIf you would like to give the addon a try yourself visit the site below to download it:\nhttps://flybywiresim.com/\n\n🔔 If you like this video please consider to subscribe to my channel: https://bit.ly/34eNWDP 🔔 \n\nAddon spotlight playlist: https://bit.ly/32nmUHH\nWebsite: https://highintheflightsimsky.nl\n\n#FlightSimulator2020 #FlightSim #FS2020",
  "thumbnail": "https://i.ytimg.com/vi/14KSXN6C9b4/sddefault.jpg",
  "thumbnailMedium": "https://i.ytimg.com/vi/14KSXN6C9b4/mqdefault.jpg",
  "publishedAt": "2022-03-13T14:02:11.000Z",
  "duration": 252,
  "tags": [
    "Flight Simulator 2020",
    "microsoft flight simulator",
    "flight simulator",
    "microsoft flight simulator 2020",
    "msfs 2020",
    "Autopilot doesn't follow GPS after loading flight",
    "A32nx autopilot doesn't follow flight plan"
  ],
  "featured": false
}