{
  "videoId": "2UF7s6IwaJ4",
  "title": "Flight Simulator 2020 - How to - A32NX - Remotely control the MCDU",
  "description": "In this video we will look at the latest developer version of the A32NX. The people from FlyByWire created an end of the year present for flight simmers by adding the option to remotely control the MCDY either by using the browser on the same machine or by using for example a Android tablet or iPad. In this video we will go to each step and will finish with a short demo using an iPad.\n\nIf you would like to give the addon a try yourself visit the site below to download it:\nhttps://flybywiresim.com/\n\n🔔 If you like this video please consider to subscribe to my channel: https://bit.ly/34eNWDP 🔔 \n\nAddon spotlight playlist: https://bit.ly/32nmUHH\nWebsite: https://highintheflightsimsky.nl\n\n#FlightSimulator2020 #FlightSim #FS2020",
  "thumbnail": "https://i.ytimg.com/vi/2UF7s6IwaJ4/sddefault.jpg",
  "thumbnailMedium": "https://i.ytimg.com/vi/2UF7s6IwaJ4/mqdefault.jpg",
  "publishedAt": "2021-12-30T13:31:00.000Z",
  "duration": 307,
  "tags": [
    "Flight Simulator 2020",
    "microsoft flight simulator",
    "flight simulator",
    "microsoft flight simulator 2020",
    "msfs 2020",
    "Remotely control MCDU in MSFS 2020",
    "Remotely control MCDU of A32 in MSFS2020",
    "Control MCDU of A32NX using iPad"
  ],
  "featured": false
}