{
  "videoId": "cBwyDdj4KD8",
  "title": "Flight Simulator 2020 - Addon spotlight - Navigraph - Avionics plugin",
  "description": "In this video we will have a look at the avionics plugin from Navigraph which has been released a few days ago. Using this addon you will have access to the different doc's/maps available for the different sections of the flight. Additionally it will add an option to import your flight plan directly into MSFS. \n\n🔔 If you like this video please consider to subscribe to my channel: https://bit.ly/34eNWDP 🔔 \n\nAddon spotlight playlist: https://bit.ly/32nmUHH\nWebsite: https://highintheflightsimsky.nl\n\n#FlightSimulator2020 #FlightSim #FS2020",
  "thumbnail": "https://i.ytimg.com/vi/cBwyDdj4KD8/sddefault.jpg",
  "thumbnailMedium": "https://i.ytimg.com/vi/cBwyDdj4KD8/mqdefault.jpg",
  "publishedAt": "2023-05-30T19:18:12.000Z",
  "duration": 380,
  "tags": [
    "Flight Simulator 2020",
    "microsoft flight simulator",
    "flight simulator",
    "microsoft flight simulator 2020",
    "msfs 2020",
    "Navigraph",
    "Simbrief",
    "Navigraph avionics plugin",
    "simbrief integration"
  ],
  "featured": false
}