{
  "videoId": "eQHzeOU6Crs",
  "title": "Flight Simulator 2020 -  Addon spotlight - Van RV-7 - version 1.0",
  "description": "A new airplane has been released for MSFS 2020: the Van RV-7. This two seater aircraft is still under development but I am really impressed already by the quality of the aircraft. Almost everything is working and besides some small bugs it is ready to go airborne. After reviewing the outside we continue with the inside and take the aircraft out for a short flight.\n\n0:00 intro video\n0:10 start of the external and internal review\n01:52 starting the engine \n06:10 take off\n08:27 testing the autopilot\n14:27 landing\n\nIf you want to try the aircraft yourself please download it from the site below:\nhttps://flightsim.to/file/23192/van-s-rv-7\n\n🔔 If you like this video please consider to subscribe to my channel: https://bit.ly/34eNWDP 🔔 \n\nAddon spotlight playlist: https://bit.ly/32nmUHH\nWebsite: https://highintheflightsimsky.nl\n\n#FlightSimulator2020 #FlightSim #FS2020",
  "thumbnail": "https://i.ytimg.com/vi/eQHzeOU6Crs/sddefault.jpg",
  "thumbnailMedium": "https://i.ytimg.com/vi/eQHzeOU6Crs/mqdefault.jpg",
  "publishedAt": "2021-11-08T20:20:07.000Z",
  "duration": 974,
  "tags": [
    "Flight Simulator 2020",
    "flight plan",
    "microsoft flight simulator",
    "flight simulator",
    "microsoft flight simulator 2020",
    "flight sim 2020",
    "Van RV-7 available for MSFS 2020",
    "Van RV-7 version 1.0 released for MSFS 2020",
    "Flying a Van RV-7 in MSFS 2020"
  ],
  "featured": false
}