{
  "videoId": "hFL-2_Mbn50",
  "title": "Flight Simulator 2020 - Addon spotlight - Working Title G3000 v0.7.1",
  "description": "Working Title updated their release of the Garmin G3000 system to version 0.7.1. In this video I will show you the enhancements made by the developers compared to the previous versions they released. \n\nIf you want to try the Working Title G3000 system yourself please download it from the site below:\nhttps://www.workingtitle.aero/packages/g3000/2021/05/21/g3000-release-v0.7.1.html\n\n🔔 If you like this video please consider to subscribe to my channel: https://bit.ly/34eNWDP 🔔 \n\nAddon spotlight playlist: https://bit.ly/32nmUHH\nWebsite: https://highintheflightsimsky.nl\n\n#FlightSimulator2020 #FlightSim #FS2020",
  "thumbnail": "https://i.ytimg.com/vi/hFL-2_Mbn50/sddefault.jpg",
  "thumbnailMedium": "https://i.ytimg.com/vi/hFL-2_Mbn50/mqdefault.jpg",
  "publishedAt": "2021-05-27T20:15:01.000Z",
  "duration": 584,
  "tags": [
    "Flight Simulator 2020",
    "microsoft flight simulator",
    "flight simulator",
    "microsoft flight simulator 2020",
    "msfs 2020",
    "Update the Daher TBM 930 flight system",
    "Working Title G3000 mod for MSFS 2020",
    "Updating the Daher TMB 930 with the Working Title G3000 mod",
    "Showing road information using the working title G3000 mod",
    "Working Title G3000 v 0.7.1",
    "Working Title G3000 updated",
    "Working Title G3000 for MSFS 2020 updated"
  ],
  "featured": false
}