{
  "videoId": "Js7x2LGAeKQ",
  "title": "Flight Simulator 2020 - POI's - Norway - Heddal Stave Church",
  "description": "In this video we will fly over the Heddal Stave Church. The Heddal Stave Church  is a parish church of the Church of Norway in Notodden Municipality in Vestfold og Telemark county, Norway. It is located in the village of Heddal. It is the church for the Heddal parish which is part of the Øvre Telemark prosti (deanery) in the Diocese of Agder og Telemark. The wooden, triple nave stave church was built in a long church design around the year 1200 using plans drawn up by an unknown architect. The church seats about 180 people.\n\n🔔 If you like this video please consider to subscribe to my channel: https://bit.ly/34eNWDP 🔔 \n\nPOI playlist: https://bit.ly/3OX9zwv\nWebsite: https://highintheflightsimsky.nl\n\n#FlightSimulator2020 #FlightSim #FS2020 #shorts",
  "thumbnail": "https://i.ytimg.com/vi/Js7x2LGAeKQ/sddefault.jpg",
  "thumbnailMedium": "https://i.ytimg.com/vi/Js7x2LGAeKQ/mqdefault.jpg",
  "publishedAt": "2023-02-05T12:44:06.000Z",
  "duration": 50,
  "tags": [
    "Flight Simulator 2020",
    "flight plan",
    "microsoft flight simulator",
    "flight simulator",
    "microsoft flight simulator 2020",
    "msfs 2020",
    "flight sim 2020",
    "low altitude flight",
    "POI",
    "handcrafted",
    "handcrafted poi",
    "Heddal Stave Church"
  ],
  "featured": false
}