{
  "videoId": "o8I86xXeFs0",
  "title": "Flight Simulator 2020- MSFS Update - Dune Expansion - Now available",
  "description": "In this video we will have a look at the Dune Expansion package which has been released yesterday. Besides a new aircraft the package will also add several tutorials and missions to MSFS 2020 so new challenges are available for you now!\n\n0:00 intro\n0:10 how to get the Dune expansion\n1:32 what is included in the Dune expansion\n\n🔔 If you like this video please consider to subscribe to my channel: https://bit.ly/34eNWDP 🔔 \n\nTutorials playlist: https://bit.ly/32nmUHH\nWebsite: https://highintheflightsimsky.nl\n\n#FlightSimulator2020 #FlightSim #FS2020",
  "thumbnail": "https://i.ytimg.com/vi/o8I86xXeFs0/sddefault.jpg",
  "thumbnailMedium": "https://i.ytimg.com/vi/o8I86xXeFs0/mqdefault.jpg",
  "publishedAt": "2024-02-14T21:09:38.000Z",
  "duration": 291,
  "tags": [
    "Flight Simulator 2020",
    "microsoft flight simulator",
    "flight simulator",
    "microsoft flight simulator 2020",
    "msfs 2020",
    "flight sim 2020",
    "aircraft update",
    "Dune 2",
    "Dune Expansion",
    "Dune expansion msfs"
  ],
  "featured": false
}