{
  "videoId": "sBQfWcu6dHI",
  "title": "Flight Simulator 2020 - How to - Using simBrief with flybywire A32NX",
  "description": "In this how to we are going to look at how to plan a flight using simBrief and load it directly into our airplane using the flybywire A32NX addon for Microsoft Flight Simulator 2020.\n\nAS320NX can be downloaded from this site: https://flybywiresim.com/a32nx\n\nThe tool used to plan our flight simBrief can be found here: https://www.simbrief.com \n\n🔔 If you like this video please consider to subscribe to my channel: https://bit.ly/34eNWDP 🔔 \n\nTutorials playlist: https://bit.ly/32nmUHH\nWebsite: https://highintheflightsimsky.nl\n\n#FlightSimulator2020 #FlightSim #FS2020",
  "thumbnail": "https://i.ytimg.com/vi/sBQfWcu6dHI/sddefault.jpg",
  "thumbnailMedium": "https://i.ytimg.com/vi/sBQfWcu6dHI/mqdefault.jpg",
  "publishedAt": "2020-12-21T12:46:16.000Z",
  "duration": 1252,
  "tags": [
    "Flight Simulator 2020",
    "flight plan",
    "microsoft flight simulator",
    "flight simulator",
    "microsoft flight simulator 2020",
    "msfs 2020",
    "tutorials",
    "flight sim 2020",
    "flybywire A32NX",
    "How to use the flybywire A32NX addon",
    "How to use simBrief.com and flybywire A32NX addon",
    "Simbrief.com integration flybywire A32NX",
    "Plan a flight using simbrief.com",
    "How to use simBrief and flybywire A32NX addon",
    "Plan a flight using simBrief",
    "How to plan a flight using simBrief"
  ],
  "featured": false
}