{
  "videoId": "U6IgS6HKkz4",
  "title": "Flight Simulator 2020 - POI's - London - bridge tour",
  "description": "In this video we will perform a low altitude flight and performing a bridge tour in parallel while flying over the Thames, Londen, United Kingdom. We will start at the Waterloo bridge and finish flying between the pillars of the Tower bridge.\n\n🔔 If you like this video please consider to subscribe to my channel: https://bit.ly/34eNWDP 🔔 \n\nPOI playlist: https://bit.ly/3OX9zwv\nWebsite: https://highintheflightsimsky.nl\n\n#FlightSimulator2020 #FlightSim #FS2020 #shorts",
  "thumbnail": "https://i.ytimg.com/vi/U6IgS6HKkz4/sddefault.jpg",
  "thumbnailMedium": "https://i.ytimg.com/vi/U6IgS6HKkz4/mqdefault.jpg",
  "publishedAt": "2022-07-05T17:45:00.000Z",
  "duration": 49,
  "tags": [
    "Flight Simulator 2020",
    "flight plan",
    "microsoft flight simulator",
    "flight simulator",
    "microsoft flight simulator 2020",
    "msfs 2020",
    "flight sim 2020",
    "low altitude flight",
    "POI",
    "handcrafted",
    "handcrafted poi",
    "London",
    "bridges",
    "Tower bridge",
    "Waterloo bridge"
  ],
  "featured": false
}